{
    "9507573641103": {
        "contentMetadata": {
            "MENTION": "{\"MENTIONEES\":[{\"M\":\"ue964b0f638a2965e5c809b1ef6421119\",\"E\":\"12\",\"S\":\"0\"}]}",
            "PREVIEW_URL_ENABLED": "true"
        },
        "contentType": 0,
        "createdTime": 1552481219919,
        "from": "u46a8452537429539fa588f2676090319",
        "text": "@Ria Agustin ayoookk mbak... Sepi ko "
    },
    "9507575220403": {
        "contentMetadata": {},
        "contentType": 0,
        "createdTime": 1552481236156,
        "from": "ud134cbd020e975960892558a13aa6dba",
        "text": "Unsend 3"
    },
    "9507575379441": {
        "contentMetadata": {
            "MENTION": "{\"MENTIONEES\":[{\"S\":\"0\",\"E\":\"12\",\"M\":\"u16d91c94c7cb6c53de85869706f60f96\"}]}"
        },
        "contentType": 0,
        "createdTime": 1552481237883,
        "from": "u931cfd7313b63713383b60149e0166cf",
        "text": "@\u2570\u2500\u2550\u0939\u0908\ufdfdBejo\ufdfd \nnek qu mati om"
    },
    "9507575782861": {
        "contentMetadata": {},
        "contentType": 0,
        "createdTime": 1552481241977,
        "from": "u931cfd7313b63713383b60149e0166cf",
        "text": ".me"
    },
    "9507576478047": {
        "contentMetadata": {},
        "contentType": 0,
        "createdTime": 1552481249139,
        "from": "u931cfd7313b63713383b60149e0166cf",
        "text": ".me"
    },
    "9507577763804": {
        "createdTime": 1552481262307,
        "from": "u931cfd7313b63713383b60149e0166cf",
        "sticker": "http://dl.stickershop.line.naver.jp/stickershop/v1/sticker/15741533/android/sticker.png"
    },
    "9507578028126": {
        "createdTime": 1552481265039,
        "from": "u931cfd7313b63713383b60149e0166cf",
        "sticker": "http://dl.stickershop.line.naver.jp/stickershop/v1/sticker/35353622/android/sticker.png"
    },
    "9507578985376": {
        "contentMetadata": {},
        "contentType": 0,
        "createdTime": 1552481274843,
        "from": "ud134cbd020e975960892558a13aa6dba",
        "text": "Unsend anu"
    },
    "9507602270205": {
        "contentMetadata": {},
        "contentType": 0,
        "createdTime": 1552481512937,
        "from": "ue964b0f638a2965e5c809b1ef6421119",
        "text": "Yooookkkkkkk"
    },
    "9507602642723": {
        "createdTime": 1552481516699,
        "from": "ue964b0f638a2965e5c809b1ef6421119",
        "sticker": "http://dl.stickershop.line.naver.jp/stickershop/v1/sticker/52114146/android/sticker.png"
    },
    "9507606461857": {
        "contentMetadata": {
            "MENTION": "{\"MENTIONEES\":[{\"M\":\"ue964b0f638a2965e5c809b1ef6421119\",\"E\":\"12\",\"S\":\"0\"}]}",
            "PREVIEW_URL_ENABLED": "true"
        },
        "contentType": 0,
        "createdTime": 1552481555695,
        "from": "u46a8452537429539fa588f2676090319",
        "text": "@Ria Agustin cekelan seng kenceng mbak"
    },
    "9507606762502": {
        "createdTime": 1552481558782,
        "from": "u1deaacd4e7c2bb734787a52d14fb31ec",
        "image": "client.png"
    },
    "9507607586544": {
        "contentMetadata": {},
        "contentType": 0,
        "createdTime": 1552481567107,
        "from": "u46a8452537429539fa588f2676090319",
        "text": "Ceblok ga iso wik Wik Wik "
    },
    "9507608081420": {
        "createdTime": 1552481572195,
        "from": "u46a8452537429539fa588f2676090319",
        "sticker": "http://dl.stickershop.line.naver.jp/stickershop/v1/sticker/15609238/android/sticker.png"
    },
    "9507610736879": {
        "createdTime": 1552481599076,
        "from": "u30b9731d0bad274fdfa83515b5baff20",
        "sticker": "http://dl.stickershop.line.naver.jp/stickershop/v1/sticker/138/android/sticker.png"
    },
    "9507611241218": {
        "contentMetadata": {},
        "contentType": 0,
        "createdTime": 1552481604246,
        "from": "u30b9731d0bad274fdfa83515b5baff20",
        "text": "Mantap"
    },
    "9507622639257": {
        "contentMetadata": {},
        "contentType": 0,
        "createdTime": 1552481718817,
        "from": "u1deaacd4e7c2bb734787a52d14fb31ec",
        "text": "Kuangen poll"
    },
    "9507625270338": {
        "contentMetadata": {},
        "contentType": 0,
        "createdTime": 1552481745037,
        "from": "u30b9731d0bad274fdfa83515b5baff20",
        "text": "Njalukk"
    },
    "9507629588485": {
        "contentMetadata": {
            "MENTION": "{\"MENTIONEES\":[{\"S\":\"0\",\"E\":\"8\",\"M\":\"u30b9731d0bad274fdfa83515b5baff20\"}]}",
            "PREVIEW_URL_ENABLED": "true"
        },
        "contentType": 0,
        "createdTime": 1552481788106,
        "from": "u8e462bd59bb4c62dc505fc93fbad36c9",
        "text": "@wiro212 dalem mas.lg join lgu.ultah.nembe iso 1"
    },
    "9507631302295": {
        "contentMetadata": {},
        "contentType": 0,
        "createdTime": 1552481805223,
        "from": "u30b9731d0bad274fdfa83515b5baff20",
        "text": "Yo cepetan"
    },
    "9507633025988": {
        "contentMetadata": {
            "MENTION": "{\"MENTIONEES\":[{\"S\":\"0\",\"E\":\"20\",\"M\":\"u1deaacd4e7c2bb734787a52d14fb31ec\"}]}",
            "PREVIEW_URL_ENABLED": "true"
        },
        "contentType": 0,
        "createdTime": 1552481822440,
        "from": "u8e462bd59bb4c62dc505fc93fbad36c9",
        "text": "@\u2550\u0926\u0987~B\u00fc\u00f1d\u00e4 \u00c7\u00ef\u00f1t\u00e5\u2550\u0987\u0926~ bun ulak.an kok lucu.hehee"
    },
    "9507638960201": {
        "contentMetadata": {
            "MENTION": "{\"MENTIONEES\":[{\"S\":\"0\",\"E\":\"14\",\"M\":\"u46a8452537429539fa588f2676090319\"}]}",
            "PREVIEW_URL_ENABLED": "true"
        },
        "contentType": 0,
        "createdTime": 1552481881603,
        "from": "ue964b0f638a2965e5c809b1ef6421119",
        "text": "@@\ud83d\ude0d BILQIS\ud83d\ude0d@ wes cekelan anu iki say,,aduuuhhh mau empuk kok dadi atos iki,,piye ikiiiii"
    },
    "9507639037011": {
        "contentMetadata": {},
        "contentType": 0,
        "createdTime": 1552481882328,
        "from": "u8e462bd59bb4c62dc505fc93fbad36c9",
        "text": "sik dalam pngawasan aq..pokus kro si mbah.opo mneh saiki onok.ccv.e\ud83d\ude23\ud83d\ude23\ud83d\ude23\ud83d\ude23\ud83d\ude23"
    },
    "9507639161380": {
        "createdTime": 1552481883562,
        "from": "ue964b0f638a2965e5c809b1ef6421119",
        "sticker": "http://dl.stickershop.line.naver.jp/stickershop/v1/sticker/41262561/android/sticker.png"
    },
    "9507646310367": {
        "contentMetadata": {},
        "contentType": 0,
        "createdTime": 1552481954784,
        "from": "u931cfd7313b63713383b60149e0166cf",
        "text": ".me"
    },
    "9507646864647": {
        "contentMetadata": {
            "height": "172",
            "locKey": "BH",
            "mediaOid": "svc=myhome|sid=h|oid=ec868520d01c5a368d368cd0d0f4499d",
            "mediaType": "V",
            "officialName": "\ud835\udcdf\ud835\udcea\ud835\udcf7\ud835\udcea\ud835\udced\ud835\udcf8\ud835\udcf5\ud835\udcf5_\ud835\udcde\ud835\udd02\ud835\udcee\ud835\udcfb\ud835\udcfb",
            "postEndUrl": "line://home/post?userMid=u70a4dfd569775f2fb1b6abbea7f55a10&postId=1155248184308067492",
            "previewMedias": "[{\"mediaOid\":\"svc=myhome|sid=h|oid=ec868520d01c5a368d368cd0d0f4499d\",\"mediaType\":\"V\"}]",
            "serviceName": "\ud835\udcdf\ud835\udcea\ud835\udcf7\ud835\udcea\ud835\udced\ud835\udcf8\ud835\udcf5\ud835\udcf5_\ud835\udcde\ud835\udd02\ud835\udcee\ud835\udcfb\ud835\udcfb",
            "serviceType": "MH",
            "text": "akhir nya dapat ya allah vedeo aslinya.\n\u2764\u2764\u2764\u2764\u2764\n",
            "width": "306"
        },
        "contentType": 16,
        "createdTime": 1552481960523,
        "from": "u70a4dfd569775f2fb1b6abbea7f55a10",
        "text": "POSTNOTIFICATION"
    },
    "9507646920879": {
        "contentMetadata": {},
        "contentType": 0,
        "createdTime": 1552481960884,
        "from": "uce9aec562ef346339bc6d0016c4543e1",
        "text": "\u2554\u2550\u2550\u2550\u2550[ \u1d18\u1d0fs\u1d1b \u1d05\u1d07\u1d1b\u1d00\u026a\u029f ]\n\u2560\u261b \u1d00\u1d1c\u1d1b\u029c\u1d0f\u0280 : \ud835\udcdf\ud835\udcea\ud835\udcf7\ud835\udcea\ud835\udced\ud835\udcf8\ud835\udcf5\ud835\udcf5_\ud835\udcde\ud835\udd02\ud835\udcee\ud835\udcfb\ud835\udcfb\n\u2560\u261b Url : https://line.me/R/home/post?userMid=u70a4dfd569775f2fb1b6abbea7f55a10&postId=1155248184308067492\n\u2560\u261b \u1d1c\u0280\u029f \u1d0d\u1d07\u1d05\u026a\u1d00 : https://obs-us.line-apps.com/myhome/h/download.nhn?oid=ec868520d01c5a368d368cd0d0f4499d\n\u2560\u261b \u1d1c\u0280\u029f \u1d0f\u0299\u1d0a\u1d07\u1d04\u1d1b : https://obs-us.line-apps.com/myhome/h/download.nhn?tid=612w&oid=ec868520d01c5a368d368cd0d0f4499d\n\u2560\u261b \u0274\u1d0f\u1d1b\u1d07 : akhir nya dapat ya allah vedeo aslinya.\n\u2764\u2764\u2764\u2764\u2764\n\n\u255a\u2550\u2550[ s\u1d07\u0280\u1d05\u1d00\u1d05\u1d1c \u029f\u1d00\u0274\u0262\u026a\u1d1b ]"
    },
    "9507646920880": {
        "contentMetadata": {},
        "contentType": 0,
        "createdTime": 1552481960895,
        "from": "uce9aec562ef346339bc6d0016c4543e1",
        "text": "\u001a \u1d05\u1d07\u1d1b\u1d00\u026a\u029f \u1d18\u1d0fs\u1d1b\u026a\u0274\u0262\u1d00\u0274 \u001a\n\u1d18\u1d07\u0274\u1d1c\u029f\u026as : \ud835\udcdf\ud835\udcea\ud835\udcf7\ud835\udcea\ud835\udced\ud835\udcf8\ud835\udcf5\ud835\udcf5_\ud835\udcde\ud835\udd02\ud835\udcee\ud835\udcfb\ud835\udcfb\n\u1d0d\u1d07\u1d05\u026a\u1d00 \u1d1c\u0280\u029f : https://obs-us.line-apps.com/myhome/h/download.nhn?oid=ec868520d01c5a368d368cd0d0f4499d\n\u1d0f\u0299\u1d0a\u1d07\u1d0b \u1d1c\u0280\u029f : https://obs-us.line-apps.com/myhome/h/download.nhn?tid=612w&oid=ec868520d01c5a368d368cd0d0f4499d\n\u1d18\u1d0fs\u1d1b \u1d1c\u0280\u029f : https://line.me/R/home/post?userMid=u70a4dfd569775f2fb1b6abbea7f55a10&postId=1155248184308067492\n\u1d1b\u1d1c\u029f\u026as\u1d00\u0274 : akhir nya dapat ya allah vedeo aslinya.\n\u2764\u2764\u2764\u2764\u2764\n"
    },
    "9507646932791": {
        "contentMetadata": {
            "ALT_TEXT": "AutoLike by jams",
            "BACKGROUND_COLOR": "00FFFFFF",
            "HTML_CONTENT": "<!doctype html><html><head><meta charset=\"UTF-8\"><meta name=\"viewport\" content=\"width=device-width, user-scalable=no, initial-scale=1, maximum-scale=1\"><meta name=\"format-detection\" content=\"telephone=no\"><script>var g=window;g.isReady=false;g.isException=false;g.ERR=function(){if(typeof g._htmlMsg===\"object\"){if(typeof g._htmlMsg.showErrorView===\"function\"){g._htmlMsg.showErrorView()}}};g.OERR=function(){g.isException=true;if(g.isReady){global.ERR()}};</script><link rel=\"stylesheet\" type=\"text/css\" href=\"https://d.line-scdn.net/n/line_flexible_msg/css/sp/main_1528964069.css\"><style type=\"text/css\">.fxC1 { color: #f0f8ff !important; } .fxC0 { background-color: #000000 !important; } </style></head><body style=\"margin: 0;\"><div class=\"T1 fxLTR\" dir=\"ltr\"><div class=\"t1Body fxC0\"><div class=\"spcSm MdBx vr\"><div class=\"MdBx vr\"><div class=\"MdBx hr bl\"><div class=\"MdIco fl0 ExLg\"><div><span style=\"background-image:url('https://obs.line-scdn.net/0hMQureOtqEn5ICzicrM9tKXROHBM_JRQ2MGtcSGheGxthPF0ucmkKGzpYTB1iawZ7ID1bT2kPHE5k'); width:1em;\"></span></div></div><div class=\"fxC1 MdTxt ExLNone ExSm ExWrap\" data-url=\"line://nv/profilePopup/mid=uc66a26f635ba47a1e95174652660585f\"><p>\u00b0\u2742\u00b0\u2742\u27a4L\u026a\u1d0b\u1d07 S\u1d1c\u1d04\u1d04\u1d07ss  \ud835\udcdf\ud835\udcea\ud835\udcf7\ud835\udcea\ud835\udced\ud835\udcf8\ud835\udcf5\ud835\udcf5_\ud835\udcde\ud835\udd02\ud835\udcee\ud835\udcfb\ud835\udcfb</p></div></div></div></div></div></div><script src=\"https://d.line-scdn.net/n/line_flexible_msg/js/app_1535978521.js\"></script><script>(function(global){var m;if(typeof global.FM===\"function\"){m=new global.FM}if(typeof global.htmlMsgScrollOut===\"undefined\"){global.htmlMsgScrollOut=function(){}}global.htmlMsgReady=function(env,state){global.isReady=true;if(global.isException||typeof m===\"undefined\"){global.ERR()}else{m.ready(env,state)}}})(window);</script></body></html>",
            "USE_FULL_WIDTH": "false",
            "USE_HORIZONTAL_SCROLL": "false",
            "USE_ROUND_CORNER": "false",
            "WIDTH_DIP": "300"
        },
        "contentType": 4,
        "createdTime": 1552481961089,
        "from": "uc66a26f635ba47a1e95174652660585f",
        "text": null
    },
    "9507646943247": {
        "contentMetadata": {},
        "contentType": 0,
        "createdTime": 1552481961104,
        "from": "u154cf8a1825351156a6d10981e1ff1af",
        "text": "Done Like !!"
    },
    "9507646947408": {
        "contentMetadata": {},
        "contentType": 0,
        "createdTime": 1552481961145,
        "from": "u566e919b625a8bbd291862643379c3f8",
        "text": "\u256d\u2550\u2550\u2550\u2550\u2550\u2550\u2550\u2550\u2550\u2550\u2550\u2550\u2550\u2550\u2550\u2550\u2550\u256e\n  \u00bb \u1d05\u1d07\u1d1b\u1d07\u1d04\u1d1b\u00a0\u1d18\u1d0fs\u1d1b\u00a0\u0299\u028f:\u00a0\u1d1b\u029c\u0299 \u1d1b\u1d07\u1d00\u1d0d\n  \u00bb \u1d00\u1d1c\u1d1b\u1d0f\u029f\u026a\u1d0b\u1d07\u00a0\u029c\u1d00s\u00a0\u0299\u1d07\u1d07\u0274\u00a0s\u1d07\u0274\u1d1b\n\u2570\u2550\u2550\u2550\u2550\u2550\u2550\u2550\u2550\u2550\u2550\u2550\u2550\u2550\u2550\u2550\u2550\u2550\u256f"
    },
    "9507646951031": {
        "contentMetadata": {
            "ALT_TEXT": "IYAN \u1d04\u0299\u0280\u00a0\u1d1b\u029c\u1d07\u00a0\u0299\u274d\u1d1bs",
            "BACKGROUND_COLOR": "00FFFFFF",
            "HTML_CONTENT": "<!doctype html><html><head><meta charset=\"UTF-8\"><meta name=\"viewport\" content=\"width=device-width, user-scalable=no, initial-scale=1, maximum-scale=1\"><meta name=\"format-detection\" content=\"telephone=no\"><script>var g=window;g.isReady=false;g.isException=false;g.ERR=function(){if(typeof g._htmlMsg===\"object\"){if(typeof g._htmlMsg.showErrorView===\"function\"){g._htmlMsg.showErrorView()}}};g.OERR=function(){g.isException=true;if(g.isReady){global.ERR()}};</script><link rel=\"stylesheet\" type=\"text/css\" href=\"https://d.line-scdn.net/n/line_flexible_msg/css/sp/main_1528964069.css\"><style type=\"text/css\">.fxC1 { color: #ffff00 !important; } .fxC4 { background-color: #00ff00 !important; } .fxC0 { background-color: #000000 !important; } .fxC3 { border-color: #ffff00 !important; } .fxC2 { border-color: #ff0000 !important; } </style></head><body style=\"margin: 0;\"><div class=\"T1 fxLTR\" dir=\"ltr\"><div class=\"ExHasFooter t1Body fxC0\"><div class=\"spcMd MdBx vr\"><div class=\"spcMd MdBx hr\"><div class=\"fxC1 MdTxt ExSm ExWrap\"><p>\u2720\u1d00\u0332\u0305\u0332\u0305\u1d1c\u0332\u0305\u0332\u0305\u1d1b\u0332\u0305\u0332\u0305\u1d0f\u0332\u0305\u0332\u0305 \u0332\u0305\u0332\u0305\u029f\u0332\u0305\u0332\u0305\u026a\u0332\u0305\u0332\u0305\u1d0b\u0332\u0305\u0332\u0305\u1d07\u0332\u0305\u2720</p><p>\u256d----------\u256e</p><p>(\u2732\u272a\u203f\u272a)\uff89</p><p>&lt;,\u2740\u2740\u2740,&gt;  \u27a0 \u27a0</p><p>  |_____|  \u029f\u026a\u1d0b\u1d07 \ud83d\ude03</p><p>_/        \\_s\u1d1c\u1d04\u1d04\u1d07s</p></div><div class=\"fxC2 fl0 MdSep\"></div><div class=\"MdImg ExFull ExFit\"><div><a style=\"padding-bottom:100%;\"><span style=\"background-image:url('https://obs.line-scdn.net/0hMQureOtqEn5ICzicrM9tKXROHBM_JRQ2MGtcSGheGxthPF0ucmkKGzpYTB1iawZ7ID1bT2kPHE5k');\"></span></a></div></div><div class=\"fxC3 fl0 MdSep\"></div></div></div></div><div class=\"t1Footer fxC0\"><div class=\"MdBx vr\"><div class=\"MdBx hr fl2\"><div class=\"ExBtn2 ExSm MdBtn\"><a class=\"fxC4\" href=\"http://line.me/ti/p/~iyan696\"><div>C\u029c\u1d00\u1d1b \u1d1b\u1d0f \u1d04\u01a6\u1d07\u1d00\u1d1b\u1d0f\u01a6S</div></a></div></div></div></div></div><script src=\"https://d.line-scdn.net/n/line_flexible_msg/js/app_1535978521.js\"></script><script>(function(global){var m;if(typeof global.FM===\"function\"){m=new global.FM}if(typeof global.htmlMsgScrollOut===\"undefined\"){global.htmlMsgScrollOut=function(){}}global.htmlMsgReady=function(env,state){global.isReady=true;if(global.isException||typeof m===\"undefined\"){global.ERR()}else{m.ready(env,state)}}})(window);</script></body></html>",
            "USE_FULL_WIDTH": "false",
            "USE_HORIZONTAL_SCROLL": "false",
            "USE_ROUND_CORNER": "false",
            "WIDTH_DIP": "300"
        },
        "contentType": 4,
        "createdTime": 1552481961356,
        "from": "u61db14daffaf2687b8d8c8672d49220b",
        "text": null
    },
    "9507646976241": {
        "contentMetadata": {
            "ALT_TEXT": "Mengirim Pesan",
            "BACKGROUND_COLOR": "00FFFFFF",
            "HTML_CONTENT": "<!doctype html><html><head><meta charset=\"UTF-8\"><meta name=\"viewport\" content=\"width=device-width, user-scalable=no, initial-scale=1, maximum-scale=1\"><meta name=\"format-detection\" content=\"telephone=no\"><script>var g=window;g.isReady=false;g.isException=false;g.ERR=function(){if(typeof g._htmlMsg===\"object\"){if(typeof g._htmlMsg.showErrorView===\"function\"){g._htmlMsg.showErrorView()}}};g.OERR=function(){g.isException=true;if(g.isReady){global.ERR()}};</script><link rel=\"stylesheet\" type=\"text/css\" href=\"https://d.line-scdn.net/n/line_flexible_msg/css/sp/main_1528964069.css\"><style type=\"text/css\">.fxC2 { color: #000000 !important; } .fxC0 { background-color: #ffffff !important; } .fxC1 { background-color: #000000 !important; } .fxC4 { background-color: #0000ff !important; } .fxC3 { border-color: #000000 !important; } </style></head><body style=\"margin: 0;\"><div class=\"T1 fxLTR\" dir=\"ltr\"><div class=\"ExHasFooter t1Body fxC0\"><div class=\"spcMd MdBx vr\"><div class=\"spcMd MdBx hr\"><div class=\"fxC2 MdTxt ExSm ExWrap ExWB\"><p>TRP BOTS</p><p></p><p></p><p>User :</p><p>\udbca\udd01\udbc0\udd03\ud835\udc01\udbff\udfff\udbca\udd01\udbc0\udd12\ud835\udc00\udbff\udfff\udbca\udd01\udbc0\udd0f\ud835\udc02\udbff\udfff\udbca\udd01\udbc0\udd0f\ud835\udc00\udbff\udfff\udbca\udd01\udbc0\udd14\ud835\udc13\udbff\udfff</p></div><div class=\"fxC3 fl0 MdSep\"></div><div class=\"MdImg ExMd ExFit\"><div><a style=\"padding-bottom:100%;\"><span style=\"background-image:url('https://obs.line-scdn.net/0h7LQqGDTaaGNsCEKMwewXNFBNZg4bJm4rFDx0AklaMAcUbX9nBWsgBU8JZFcWbCY0AmwmBEoBNwQW');\"></span></a></div></div></div><div class=\"fxC3 fl0 MdSep\"></div><div class=\"MdBx vr\"><div class=\"MdBx hr bl\"><div class=\"fxC2 MdTxt ExAlgC ExSm ExWrap ExWB\"><p>\u2742\u27a3 Done Like &amp; Comment</p></div></div></div></div></div><div class=\"fxC1 t1Footer\"><div class=\"MdBx vr\"><div class=\"ExBtn1 ExSm fl3 MdBtn\"><a class=\"fxC4\" href=\"http://line.me/ti/p/~thekingpain1206\"><div>\ud83c\udde8\u200c\ud83c\uddf1\u200c\ud83c\uddee\u200c\ud83c\udde8\u200c\ud83c\uddf0\u200c&nbsp;\ud83c\udded\u200c\ud83c\uddea\u200c\ud83c\uddf7\u200c\ud83c\uddea\u200c</div></a></div></div></div></div><script src=\"https://d.line-scdn.net/n/line_flexible_msg/js/app_1535978521.js\"></script><script>(function(global){var m;if(typeof global.FM===\"function\"){m=new global.FM}if(typeof global.htmlMsgScrollOut===\"undefined\"){global.htmlMsgScrollOut=function(){}}global.htmlMsgReady=function(env,state){global.isReady=true;if(global.isException||typeof m===\"undefined\"){global.ERR()}else{m.ready(env,state)}}})(window);</script></body></html>",
            "USE_FULL_WIDTH": "false",
            "USE_HORIZONTAL_SCROLL": "false",
            "USE_ROUND_CORNER": "false",
            "WIDTH_DIP": "300"
        },
        "contentType": 4,
        "createdTime": 1552481961470,
        "from": "ucb61c7eddacd46170c5fe80c300280ff",
        "text": null
    },
    "9507646977216": {
        "contentMetadata": {
            "AGENT_ICON": "https://media.giphy.com/media/xULW8HJF4HPDxYcOrK/giphy.gif",
            "AGENT_LINK": "line://nv/profilePopup/mid=ua797021910f0584e11be56d4a6fa74ed",
            "AGENT_NAME": "\u300c\u2730L\u0390mb\u0365\u0390z\u0363k\u036b\u0390\u2202\u0e23\u2730\u300d"
        },
        "contentType": 0,
        "createdTime": 1552481961450,
        "from": "uf1aa6f3bb1d71941bf99d7006890edc8",
        "text": "\u272f\u035c\u0361\u2742\u27a3 like Success"
    },
    "9507647011169": {
        "contentMetadata": {},
        "contentType": 0,
        "createdTime": 1552481961869,
        "from": "u154cf8a1825351156a6d10981e1ff1af",
        "text": "'MENTION'"
    },
    "9507647021841": {
        "contentMetadata": {
            "AGENT_ICON": "https://media.giphy.com/media/xULW8HJF4HPDxYcOrK/giphy.gif",
            "AGENT_LINK": "line://nv/profilePopup/mid=ua797021910f0584e11be56d4a6fa74ed",
            "AGENT_NAME": "\u300c\u2730L\u0390mb\u0365\u0390z\u0363k\u036b\u0390\u2202\u0e23\u2730\u300d"
        },
        "contentType": 0,
        "createdTime": 1552481961914,
        "from": "u4385f6d6d90dc5bcebb2902a986ad25f",
        "text": "\u272f\u035c\u0361\u2742\u27a3 like Success"
    },
    "9507647023889": {
        "contentMetadata": {
            "AGENT_ICON": "https://media.giphy.com/media/xULW8HJF4HPDxYcOrK/giphy.gif",
            "AGENT_LINK": "line://nv/profilePopup/mid=ua797021910f0584e11be56d4a6fa74ed",
            "AGENT_NAME": "\u300c\u2730L\u0390mb\u0365\u0390z\u0363k\u036b\u0390\u2202\u0e23\u2730\u300d"
        },
        "contentType": 0,
        "createdTime": 1552481961953,
        "from": "u3f87a7a2449793ecf3cf6280fe6fabfa",
        "text": "\u272f\u035c\u0361\u2742\u27a3 like Success"
    },
    "9507647085284": {
        "contentMetadata": {
            "AGENT_ICON": "https://media.giphy.com/media/xULW8HJF4HPDxYcOrK/giphy.gif",
            "AGENT_LINK": "line://nv/profilePopup/mid=ua797021910f0584e11be56d4a6fa74ed",
            "AGENT_NAME": "\u300c\u2730L\u0390mb\u0365\u0390z\u0363k\u036b\u0390\u2202\u0e23\u2730\u300d"
        },
        "contentType": 0,
        "createdTime": 1552481962641,
        "from": "u4385f6d6d90dc5bcebb2902a986ad25f",
        "text": "Spam terdeteksi, Saya tersiksa Di ruangan Ini /n saya akan Diam Selama 30 Detik ketik Open untuk mengaktifkan kembali."
    },
    "9507647097254": {
        "contentMetadata": {
            "ALT_TEXT": "RADISTI TEAM BOTS",
            "BACKGROUND_COLOR": "00FFFFFF",
            "HTML_CONTENT": "<!doctype html><html><head><meta charset=\"UTF-8\"><meta name=\"viewport\" content=\"width=device-width, user-scalable=no, initial-scale=1, maximum-scale=1\"><meta name=\"format-detection\" content=\"telephone=no\"><script>var g=window;g.isReady=false;g.isException=false;g.ERR=function(){if(typeof g._htmlMsg===\"object\"){if(typeof g._htmlMsg.showErrorView===\"function\"){g._htmlMsg.showErrorView()}}};g.OERR=function(){g.isException=true;if(g.isReady){global.ERR()}};</script><link rel=\"stylesheet\" type=\"text/css\" href=\"https://d.line-scdn.net/n/line_flexible_msg/css/sp/main_1528964069.css\"><style type=\"text/css\">.fxC4 { color: #ffca00 !important; } .fxC5 { color: #000000 !important; } .fxC1 { background-color: #ff1e00 !important; } .fxC0 { background-color: #000000 !important; } .fxC3 { border-color: #ff0009 !important; } .fxC2 { border-color: #ff0a00 !important; } </style></head><body style=\"margin: 0;\"><div class=\"T1 fxLTR\" dir=\"ltr\"><div class=\"ExHasFooter t1Body fxC0\"><div class=\"spcMd MdBx vr\"><div class=\"spcMd MdBx hr\"><div class=\"MdImg ExMd ExFit\"><div><a style=\"padding-bottom:100%;\"><span style=\"background-image:url('https://obs.line-scdn.net/0hX8tuFeJiBxdJDC33vJZ4QHVJCXo-IgFfMT9Ic2leCnJlP0EVfWxMeWsNUC9nOERIJWpKITwLDHQ0');\"></span></a></div></div><div class=\"fxC2 fl0 MdSep\"></div><div class=\"MdImg ExMd ExFit\"><div><a style=\"padding-bottom:100%;\"><span style=\"background-image:url('https://i.ibb.co/vd9PLVy/1549594117625.jpg');\"></span></a></div></div></div><div class=\"fxC3 fl0 MdSep\"></div><div class=\"MdBx vr\"><div class=\"MdBx hr bl\"><div class=\"MdTxt fxC4 ExWrap ExXs\"><p>Done Liked !</p></div></div></div></div></div><div class=\"fxC1 t1Footer\"><div class=\"MdBx vr\"><div class=\"MdBx hr\"><div class=\"MdBx hr bl\"><div class=\"MdTxt ExAlgC fxC5 ExWB\" data-url=\"http://line.me/ti/p/~radistiutama\"><p>RADISTI TEAM BOTS</p></div></div></div></div></div></div><script src=\"https://d.line-scdn.net/n/line_flexible_msg/js/app_1535978521.js\"></script><script>(function(global){var m;if(typeof global.FM===\"function\"){m=new global.FM}if(typeof global.htmlMsgScrollOut===\"undefined\"){global.htmlMsgScrollOut=function(){}}global.htmlMsgReady=function(env,state){global.isReady=true;if(global.isException||typeof m===\"undefined\"){global.ERR()}else{m.ready(env,state)}}})(window);</script></body></html>",
            "USE_FULL_WIDTH": "false",
            "USE_HORIZONTAL_SCROLL": "false",
            "USE_ROUND_CORNER": "false",
            "WIDTH_DIP": "300"
        },
        "contentType": 4,
        "createdTime": 1552481962747,
        "from": "ud134cbd020e975960892558a13aa6dba",
        "text": null
    },
    "9507647102704": {
        "contentMetadata": {},
        "contentType": 0,
        "createdTime": 1552481962704,
        "from": "u931cfd7313b63713383b60149e0166cf",
        "text": ".me"
    },
    "9507647106157": {
        "createdTime": 1552481962813,
        "from": "uf5ade9343fd07061ff222f79586e5cb5",
        "sticker": "http://dl.stickershop.line.naver.jp/stickershop/v1/sticker/17864/android/sticker.png"
    },
    "9507647191964": {
        "contentMetadata": {
            "AGENT_ICON": "https://media.giphy.com/media/xULW8HJF4HPDxYcOrK/giphy.gif",
            "AGENT_LINK": "line://nv/profilePopup/mid=ua797021910f0584e11be56d4a6fa74ed",
            "AGENT_NAME": "\u300c\u2730L\u0390mb\u0365\u0390z\u0363k\u036b\u0390\u2202\u0e23\u2730\u300d"
        },
        "contentType": 0,
        "createdTime": 1552481963768,
        "from": "u3f87a7a2449793ecf3cf6280fe6fabfa",
        "text": "Spam terdeteksi, Saya tersiksa Di ruangan Ini /n saya akan Diam Selama 30 Detik ketik Open untuk mengaktifkan kembali."
    },
    "9507647429445": {
        "contentMetadata": {},
        "contentType": 0,
        "createdTime": 1552481966006,
        "from": "u931cfd7313b63713383b60149e0166cf",
        "text": ".me"
    },
    "9507647987577": {
        "contentMetadata": {},
        "contentType": 0,
        "createdTime": 1552481971565,
        "from": "u931cfd7313b63713383b60149e0166cf",
        "text": ".me"
    },
    "9507650150213": {
        "contentMetadata": {
            "AGENT_ICON": "https://media.giphy.com/media/xULW8HJF4HPDxYcOrK/giphy.gif",
            "AGENT_LINK": "line://nv/profilePopup/mid=ua797021910f0584e11be56d4a6fa74ed",
            "AGENT_NAME": "\u300c\u2730L\u0390mb\u0365\u0390z\u0363k\u036b\u0390\u2202\u0e23\u2730\u300d"
        },
        "contentType": 0,
        "createdTime": 1552481993147,
        "from": "u3f87a7a2449793ecf3cf6280fe6fabfa",
        "text": "Bot kembali aktif"
    },
    "9507650194394": {
        "contentMetadata": {
            "AGENT_ICON": "https://media.giphy.com/media/xULW8HJF4HPDxYcOrK/giphy.gif",
            "AGENT_LINK": "line://nv/profilePopup/mid=ua797021910f0584e11be56d4a6fa74ed",
            "AGENT_NAME": "\u300c\u2730L\u0390mb\u0365\u0390z\u0363k\u036b\u0390\u2202\u0e23\u2730\u300d"
        },
        "contentType": 0,
        "createdTime": 1552481993687,
        "from": "u4385f6d6d90dc5bcebb2902a986ad25f",
        "text": "Bot kembali aktif"
    },
    "9507653387722": {
        "createdTime": 1552482025286,
        "from": "u46a8452537429539fa588f2676090319",
        "sticker": "http://dl.stickershop.line.naver.jp/stickershop/v1/sticker/21831483/android/sticker.png"
    },
    "9507655062460": {
        "contentMetadata": {},
        "contentType": 0,
        "createdTime": 1552482041965,
        "from": "u46a8452537429539fa588f2676090319",
        "text": "Kesuwen pean dadi atos deh"
    },
    "9507655495382": {
        "contentMetadata": {
            "EMTVER": "4",
            "MENTION": "{\"MENTIONEES\":[{\"S\":\"0\",\"E\":\"36\",\"M\":\"u931cfd7313b63713383b60149e0166cf\"}]}"
        },
        "contentType": 0,
        "createdTime": 1552482046211,
        "from": "u16d91c94c7cb6c53de85869706f60f96",
        "text": "@\udbc9\ude01\udbc0\udd0eN\udbff\udfff\udbc9\ude01\udbc0\udd05E\udbff\udfff\udbc9\ude01\udbc0\udd19Y\udbff\udfff\udbc9\ude01\udbc0\udd13S\udbff\udfff\udbc9\ude01\udbc0\udd01A\udbff\udfff login"
    },
    "9507659583311": {
        "contentMetadata": {
            "MENTION": "{\"MENTIONEES\":[{\"S\":\"0\",\"E\":\"12\",\"M\":\"u16d91c94c7cb6c53de85869706f60f96\"}]}"
        },
        "contentType": 0,
        "createdTime": 1552482087197,
        "from": "u931cfd7313b63713383b60149e0166cf",
        "text": "@\u2570\u2500\u2550\u0939\u0908\ufdfdBejo\ufdfd \nws login maeng"
    },
    "9507663104256": {
        "contentMetadata": {},
        "contentType": 0,
        "createdTime": 1552482122418,
        "from": "u931cfd7313b63713383b60149e0166cf",
        "text": "Login 1"
    },
    "9507663129051": {
        "contentMetadata": {},
        "contentType": 0,
        "createdTime": 1552482122654,
        "from": "u7d09039d85adada8b4e073f359ae379b",
        "text": "\u300c Link QR\u300d\nBerlaku Cuma 2 Menit Cepat Tekan Link\nline://au/q/HQj0PQihfX5OCMMJs3YgVz4D1synP6AS\nCreated By:[\u2605R\u035e\u035f\u0338A\u035e\u035f\u0338D\u035e\u035f\u0338I\u035e\u035f\u0338S\u035e\u035f\u0338T\u035e\u035f\u0338I\u035e\u035f\u0338 T\u035e\u035f\u0338E\u035e\u035f\u0338A\u035e\u035f\u0338M\u035e\u035f\u0338 B\u035e\u035f\u0338O\u035e\u035f\u0338T\u035e\u035f\u0338\u2605]"
    },
    "9507663610316": {
        "contentMetadata": {},
        "contentType": 0,
        "createdTime": 1552482127544,
        "from": "u7d09039d85adada8b4e073f359ae379b",
        "text": "ECrzjI6V7xv1wyFmLJef.KXZ9CXo2nXm4o2auNGfMZW.O5IAhpIzXpDozo2tgCQyzdx1bvJW4tZ0iqLYpzCCTig="
    },
    "9507663610317": {
        "contentMetadata": {},
        "contentType": 0,
        "createdTime": 1552482127575,
        "from": "u7d09039d85adada8b4e073f359ae379b",
        "text": "Simpan tokenmu dan kasihkan staff yg on jangan lupa kasih tanda"
    },
    "9507665838140": {
        "contentMetadata": {},
        "contentType": 0,
        "createdTime": 1552482149755,
        "from": "uab7203e3f207b080fde8e68bd3dd75ca",
        "text": "Login 1"
    },
    "9507665841263": {
        "contentMetadata": {},
        "contentType": 0,
        "createdTime": 1552482149944,
        "from": "u7d09039d85adada8b4e073f359ae379b",
        "text": "\u300c Link QR\u300d\nBerlaku Cuma 2 Menit Cepat Tekan Link\nline://au/q/zer379OpCyAdHQB1DF70J05XFabL43Q0\nCreated By:[\u2605R\u035e\u035f\u0338A\u035e\u035f\u0338D\u035e\u035f\u0338I\u035e\u035f\u0338S\u035e\u035f\u0338T\u035e\u035f\u0338I\u035e\u035f\u0338 T\u035e\u035f\u0338E\u035e\u035f\u0338A\u035e\u035f\u0338M\u035e\u035f\u0338 B\u035e\u035f\u0338O\u035e\u035f\u0338T\u035e\u035f\u0338\u2605]"
    },
    "9507666162285": {
        "contentMetadata": {},
        "contentType": 0,
        "createdTime": 1552482153198,
        "from": "u7d09039d85adada8b4e073f359ae379b",
        "text": "ECf5khRw05Fh9T5rtHWa.Q3id4+ihSid96oAl0911YG.2ysPurfd/dKEWo/vKYHA2MUDzYig2Zb4WBOrcJ9BbM0="
    },
    "9507666187131": {
        "contentMetadata": {},
        "contentType": 0,
        "createdTime": 1552482153253,
        "from": "u7d09039d85adada8b4e073f359ae379b",
        "text": "Simpan tokenmu dan kasihkan staff yg on jangan lupa kasih tanda"
    },
    "9507668279326": {
        "contentMetadata": {
            "MENTION": "{\"MENTIONEES\":[{\"S\":\"0\",\"E\":\"20\",\"M\":\"uf5ade9343fd07061ff222f79586e5cb5\"}]}",
            "PREVIEW_URL_ENABLED": "true"
        },
        "contentType": 0,
        "createdTime": 1552482174230,
        "from": "u80e2ba36152d056f69fff16e177abb34",
        "text": "@\ua9c1\u270d\u0361\u27b4\u035c\u09e1\u272f\u0365\u221a\u00a3$\u270d\u0361\u27b4\u035c\u09e1\u272f\u0365\ua9c1 knp kk"
    },
    "9507669649982": {
        "contentMetadata": {},
        "contentType": 0,
        "createdTime": 1552482187952,
        "from": "uf5ade9343fd07061ff222f79586e5cb5",
        "text": "Anu neng"
    },
    "9507670439080": {
        "contentMetadata": {
            "MENTION": "{\"MENTIONEES\":[{\"S\":\"0\",\"E\":\"22\",\"M\":\"u09f59671aac95d08eea489002e6917da\"}]}"
        },
        "contentType": 0,
        "createdTime": 1552482195929,
        "from": "uf5ade9343fd07061ff222f79586e5cb5",
        "text": "@\ud83c\udf3f\ud83c\udf37Ale ramadhani\ud83c\udf37\ud83c\udf3f "
    },
    "9507670960449": {
        "contentMetadata": {
            "MENTION": "{\"MENTIONEES\":[{\"S\":\"0\",\"E\":\"22\",\"M\":\"u09f59671aac95d08eea489002e6917da\"}]}"
        },
        "contentType": 0,
        "createdTime": 1552482201149,
        "from": "uf5ade9343fd07061ff222f79586e5cb5",
        "text": "@\ud83c\udf3f\ud83c\udf37Ale ramadhani\ud83c\udf37\ud83c\udf3f "
    },
    "9507671347411": {
        "contentMetadata": {
            "MENTION": "{\"MENTIONEES\":[{\"S\":\"0\",\"E\":\"16\",\"M\":\"u80e2ba36152d056f69fff16e177abb34\"}]}"
        },
        "contentType": 0,
        "createdTime": 1552482205069,
        "from": "uf5ade9343fd07061ff222f79586e5cb5",
        "text": "@\ud83d\udca5ISSC\ud83c\udf00Dhita\ud83d\udca5 "
    },
    "9507671868884": {
        "contentMetadata": {
            "MENTION": "{\"MENTIONEES\":[{\"S\":\"0\",\"E\":\"20\",\"M\":\"uf5ade9343fd07061ff222f79586e5cb5\"}]}",
            "PREVIEW_URL_ENABLED": "true"
        },
        "contentType": 0,
        "createdTime": 1552482210253,
        "from": "u80e2ba36152d056f69fff16e177abb34",
        "text": "@\ua9c1\u270d\u0361\u27b4\u035c\u09e1\u272f\u0365\u221a\u00a3$\u270d\u0361\u27b4\u035c\u09e1\u272f\u0365\ua9c1 minum obat nahh...kl puyenk"
    },
    "9507672056582": {
        "contentMetadata": {},
        "contentType": 0,
        "createdTime": 1552482212186,
        "from": "uf5ade9343fd07061ff222f79586e5cb5",
        "text": "Jempol "
    },
    "9507672260308": {
        "contentMetadata": {},
        "contentType": 0,
        "createdTime": 1552482214179,
        "from": "uf5ade9343fd07061ff222f79586e5cb5",
        "text": "Anu"
    },
    "9507672288292": {
        "contentMetadata": {
            "BOT_CHECK": "1",
            "BOT_MSGTYPE": "keyword_reply",
            "BOT_TO_MID": "cc6912edc4c7f2842e7cb1a6726a72d24"
        },
        "contentType": 0,
        "createdTime": 1552482214529,
        "from": "u292e72c4e5873a2621e3600de8f66d91",
        "text": "\u03b1\u03b7\u03c5 \u2113\u03c5\u043d \u0455\u03c5\u0454"
    },
    "9507672787377": {
        "contentMetadata": {
            "BOT_CHECK": "1",
            "BOT_MSGTYPE": "keyword_reply",
            "BOT_TO_MID": "cc6912edc4c7f2842e7cb1a6726a72d24",
            "EMTVER": "3"
        },
        "contentType": 0,
        "createdTime": 1552482219581,
        "from": "u292e72c4e5873a2621e3600de8f66d91",
        "text": "\u0192\u03c3\u043a\u03c5\u0455 \u043a\u043a \u0192\u03c3\u043a\u03c5\u0455\u0455\u0455...\n\u043d\u03b1\u2202\u0454\u0454\u0454\u0454\u043d\udbc0\udc97\udbc0\udc97"
    },
    "9507672792390": {
        "contentMetadata": {},
        "contentType": 0,
        "createdTime": 1552482219541,
        "from": "uf5ade9343fd07061ff222f79586e5cb5",
        "text": "Typo"
    },
    "9507673381483": {
        "contentMetadata": {},
        "contentType": 0,
        "createdTime": 1552482225449,
        "from": "uf5ade9343fd07061ff222f79586e5cb5",
        "text": "Slh tag"
    },
    "9507673574838": {
        "createdTime": 1552482227369,
        "from": "uf5ade9343fd07061ff222f79586e5cb5",
        "sticker": "http://dl.stickershop.line.naver.jp/stickershop/v1/sticker/17865/android/sticker.png"
    },
    "9507674240116": {
        "createdTime": 1552482234017,
        "from": "u80e2ba36152d056f69fff16e177abb34",
        "sticker": "http://dl.stickershop.line.naver.jp/stickershop/v1/sticker/521036/android/sticker.png"
    },
    "9507675175473": {
        "contentMetadata": {
            "MENTION": "{\"MENTIONEES\":[{\"S\":\"0\",\"E\":\"16\",\"M\":\"u80e2ba36152d056f69fff16e177abb34\"}]}"
        },
        "contentType": 0,
        "createdTime": 1552482243418,
        "from": "uf5ade9343fd07061ff222f79586e5cb5",
        "text": "@\ud83d\udca5ISSC\ud83c\udf00Dhita\ud83d\udca5 "
    },
    "9507675795654": {
        "createdTime": 1552482249683,
        "from": "u8d452c56de13893aabe37df65c7ba55b",
        "sticker": "http://dl.stickershop.line.naver.jp/stickershop/v1/sticker/52002764/android/sticker.png"
    },
    "9507676578124": {
        "contentMetadata": {},
        "contentType": 0,
        "createdTime": 1552482257710,
        "from": "u8d452c56de13893aabe37df65c7ba55b",
        "text": "Sugeng sare"
    },
    "9507677681877": {
        "contentMetadata": {},
        "contentType": 0,
        "createdTime": 1552482268740,
        "from": "uf5ade9343fd07061ff222f79586e5cb5",
        "text": "Neng ngalamunin"
    },
    "9507677807210": {
        "contentMetadata": {},
        "contentType": 0,
        "createdTime": 1552482270060,
        "from": "uf5ade9343fd07061ff222f79586e5cb5",
        "text": "Pa"
    },
    "9507677994882": {
        "createdTime": 1552482271897,
        "from": "uf5ade9343fd07061ff222f79586e5cb5",
        "sticker": "http://dl.stickershop.line.naver.jp/stickershop/v1/sticker/114/android/sticker.png"
    },
    "9507679215860": {
        "contentMetadata": {
            "MENTION": "{\"MENTIONEES\":[{\"S\":\"0\",\"E\":\"20\",\"M\":\"uf5ade9343fd07061ff222f79586e5cb5\"}]}",
            "PREVIEW_URL_ENABLED": "true"
        },
        "contentType": 0,
        "createdTime": 1552482284234,
        "from": "u80e2ba36152d056f69fff16e177abb34",
        "text": "@\ua9c1\u270d\u0361\u27b4\u035c\u09e1\u272f\u0365\u221a\u00a3$\u270d\u0361\u27b4\u035c\u09e1\u272f\u0365\ua9c1 bingungggg aa komat kamit nahhh"
    },
    "9507679932660": {
        "createdTime": 1552482291448,
        "from": "u80e2ba36152d056f69fff16e177abb34",
        "sticker": "http://dl.stickershop.line.naver.jp/stickershop/v1/sticker/10/android/sticker.png"
    },
    "9507680787249": {
        "createdTime": 1552482300066,
        "from": "uf5ade9343fd07061ff222f79586e5cb5",
        "sticker": "http://dl.stickershop.line.naver.jp/stickershop/v1/sticker/17864/android/sticker.png"
    },
    "9507680811688": {
        "createdTime": 1552482300295,
        "from": "u09f59671aac95d08eea489002e6917da",
        "sticker": "http://dl.stickershop.line.naver.jp/stickershop/v1/sticker/135803794/android/sticker.png"
    },
    "9507681476369": {
        "contentMetadata": {},
        "contentType": 0,
        "createdTime": 1552482306996,
        "from": "ufa0a0417d09ed00f3645c76f9da47c57",
        "text": "Me"
    },
    "9507681488888": {
        "contentMetadata": {
            "ALT_TEXT": "RADISTI TEAM BOT",
            "BACKGROUND_COLOR": "00FFFFFF",
            "HTML_CONTENT": "<!doctype html><html><head><meta charset=\"UTF-8\"><meta name=\"viewport\" content=\"width=device-width, user-scalable=no, initial-scale=1, maximum-scale=1\"><meta name=\"format-detection\" content=\"telephone=no\"><script>var g=window;g.isReady=false;g.isException=false;g.ERR=function(){if(typeof g._htmlMsg===\"object\"){if(typeof g._htmlMsg.showErrorView===\"function\"){g._htmlMsg.showErrorView()}}};g.OERR=function(){g.isException=true;if(g.isReady){global.ERR()}};</script><link rel=\"stylesheet\" type=\"text/css\" href=\"https://d.line-scdn.net/n/line_flexible_msg/css/sp/main_1528964069.css\"><style type=\"text/css\">.fxC0 { color: #2500ff !important; } .fxC1 { background-color: #0d00ff !important; } </style></head><body style=\"margin: 0;\"><div class=\"T1 fxLTR\" dir=\"ltr\"><div class=\"t1Header\"><div class=\"MdBx spcXs vr\"><div class=\"MdTxt ExAlgC fxC0 ExWrap ExWB\"><p>RADISTI TEAM BOTS</p></div></div></div><div class=\"t1Hero\"><div class=\"MdImg ExFull ExFit\"><div><a style=\"padding-bottom:100%;\"><span style=\"background-image:url('https://obs.line-scdn.net/0h-2eC-Lnrch1YOljyjdkNSmR_fHAvFHRVIAttei07KS1zXzRDMAk8eio4KyhxWDNMM1RoK3g8filz');\"></span></a></div></div></div><div class=\"ExHasFooter t1Body\"><div class=\"spcMd MdBx vr\"><div class=\"spcMd MdBx hr\"><div class=\"MdImg ExSm ExFit\"><div><a style=\"padding-bottom:100%;\"><span style=\"background-image:url('https://i.ibb.co/vd9PLVy/1549594117625.jpg');\"></span></a></div></div><div class=\"fl0 MdSep\"></div><div class=\"MdTxt ExWrap\"><p>NAMA:</p><p>\ud83e\udd82\u2767\u2765\u256c\u2550\u0f74\u0f72\u0f74\u0f72 iwedPSO\u2694\u2767\u2765</p></div></div><div class=\"fl0 MdSep\"></div><div class=\"spcMd MdBx hr\"><div class=\"MdImg ExSm ExFit\"><div><a style=\"padding-bottom:100%;\"><span style=\"background-image:url('https://info-menarik.net/wp-content/uploads/2014/11/Membuat-Animasi-Format-GIF-1.gif');\"></span></a></div></div><div class=\"fl0 MdSep\"></div><div class=\"MdTxt ExWrap ExXs\"><p>PROFILE:</p></div></div></div></div><div class=\"t1Footer\"><div class=\"MdBx vr\"><div class=\"spcMd mdBxSpacer fl0\"></div><div class=\"ExBtn1 MdBtn\"><a class=\"fxC1\" href=\"http://line.me/ti/p/~radistiutama\"><div>KLIK ME</div></a></div></div></div></div><script src=\"https://d.line-scdn.net/n/line_flexible_msg/js/app_1535978521.js\"></script><script>(function(global){var m;if(typeof global.FM===\"function\"){m=new global.FM}if(typeof global.htmlMsgScrollOut===\"undefined\"){global.htmlMsgScrollOut=function(){}}global.htmlMsgReady=function(env,state){global.isReady=true;if(global.isException||typeof m===\"undefined\"){global.ERR()}else{m.ready(env,state)}}})(window);</script></body></html>",
            "USE_FULL_WIDTH": "false",
            "USE_HORIZONTAL_SCROLL": "false",
            "USE_ROUND_CORNER": "false",
            "WIDTH_DIP": "300"
        },
        "contentType": 4,
        "createdTime": 1552482307259,
        "from": "uad0ef5680ff4b229512f93fc8e54f92f",
        "text": null
    },
    "9507681492466": {
        "createdTime": 1552482307128,
        "from": "u05b001551c897ad6a6e2ca6cecccd32e",
        "sticker": "http://dl.stickershop.line.naver.jp/stickershop/v1/sticker/149/android/sticker.png"
    },
    "9507681493248": {
        "contentMetadata": {
            "ALT_TEXT": "RADISTI TEAM BOT",
            "BACKGROUND_COLOR": "00FFFFFF",
            "HTML_CONTENT": "<!doctype html><html><head><meta charset=\"UTF-8\"><meta name=\"viewport\" content=\"width=device-width, user-scalable=no, initial-scale=1, maximum-scale=1\"><meta name=\"format-detection\" content=\"telephone=no\"><script>var g=window;g.isReady=false;g.isException=false;g.ERR=function(){if(typeof g._htmlMsg===\"object\"){if(typeof g._htmlMsg.showErrorView===\"function\"){g._htmlMsg.showErrorView()}}};g.OERR=function(){g.isException=true;if(g.isReady){global.ERR()}};</script><link rel=\"stylesheet\" type=\"text/css\" href=\"https://d.line-scdn.net/n/line_flexible_msg/css/sp/main_1528964069.css\"><style type=\"text/css\">.fxC0 { color: #2500ff !important; } .fxC1 { background-color: #0d00ff !important; } </style></head><body style=\"margin: 0;\"><div class=\"T1 fxLTR\" dir=\"ltr\"><div class=\"t1Header\"><div class=\"MdBx spcXs vr\"><div class=\"MdTxt ExAlgC fxC0 ExWrap ExWB\"><p>RADISTI TEAM BOTS</p></div></div></div><div class=\"t1Hero\"><div class=\"MdImg ExFull ExFit\"><div><a style=\"padding-bottom:100%;\"><span style=\"background-image:url('https://obs.line-scdn.net/0h-2eC-Lnrch1YOljyjdkNSmR_fHAvFHRVIAttei07KS1zXzRDMAk8eio4KyhxWDNMM1RoK3g8filz');\"></span></a></div></div></div><div class=\"ExHasFooter t1Body\"><div class=\"spcMd MdBx vr\"><div class=\"spcMd MdBx hr\"><div class=\"MdImg ExSm ExFit\"><div><a style=\"padding-bottom:100%;\"><span style=\"background-image:url('https://i.ibb.co/vd9PLVy/1549594117625.jpg');\"></span></a></div></div><div class=\"fl0 MdSep\"></div><div class=\"MdTxt ExWrap\"><p>NAMA:</p><p>\ud83e\udd82\u2767\u2765\u256c\u2550\u0f74\u0f72\u0f74\u0f72 iwedPSO\u2694\u2767\u2765</p></div></div><div class=\"fl0 MdSep\"></div><div class=\"spcMd MdBx hr\"><div class=\"MdImg ExSm ExFit\"><div><a style=\"padding-bottom:100%;\"><span style=\"background-image:url('https://info-menarik.net/wp-content/uploads/2014/11/Membuat-Animasi-Format-GIF-1.gif');\"></span></a></div></div><div class=\"fl0 MdSep\"></div><div class=\"MdTxt ExWrap ExXs\"><p>PROFILE:</p></div></div></div></div><div class=\"t1Footer\"><div class=\"MdBx vr\"><div class=\"spcMd mdBxSpacer fl0\"></div><div class=\"ExBtn1 MdBtn\"><a class=\"fxC1\" href=\"http://line.me/ti/p/~radistiutama\"><div>KLIK ME</div></a></div></div></div></div><script src=\"https://d.line-scdn.net/n/line_flexible_msg/js/app_1535978521.js\"></script><script>(function(global){var m;if(typeof global.FM===\"function\"){m=new global.FM}if(typeof global.htmlMsgScrollOut===\"undefined\"){global.htmlMsgScrollOut=function(){}}global.htmlMsgReady=function(env,state){global.isReady=true;if(global.isException||typeof m===\"undefined\"){global.ERR()}else{m.ready(env,state)}}})(window);</script></body></html>",
            "USE_FULL_WIDTH": "false",
            "USE_HORIZONTAL_SCROLL": "false",
            "USE_ROUND_CORNER": "false",
            "WIDTH_DIP": "300"
        },
        "contentType": 4,
        "createdTime": 1552482307187,
        "from": "u1ea07366e4db7c890cc3dd80aad4c96f",
        "text": null
    },
    "9507681493249": {
        "contentMetadata": {
            "ALT_TEXT": "RADISTI TEAM BOT",
            "BACKGROUND_COLOR": "00FFFFFF",
            "HTML_CONTENT": "<!doctype html><html><head><meta charset=\"UTF-8\"><meta name=\"viewport\" content=\"width=device-width, user-scalable=no, initial-scale=1, maximum-scale=1\"><meta name=\"format-detection\" content=\"telephone=no\"><script>var g=window;g.isReady=false;g.isException=false;g.ERR=function(){if(typeof g._htmlMsg===\"object\"){if(typeof g._htmlMsg.showErrorView===\"function\"){g._htmlMsg.showErrorView()}}};g.OERR=function(){g.isException=true;if(g.isReady){global.ERR()}};</script><link rel=\"stylesheet\" type=\"text/css\" href=\"https://d.line-scdn.net/n/line_flexible_msg/css/sp/main_1528964069.css\"><style type=\"text/css\">.fxC0 { color: #2500ff !important; } .fxC1 { background-color: #0d00ff !important; } </style></head><body style=\"margin: 0;\"><div class=\"T1 fxLTR\" dir=\"ltr\"><div class=\"t1Header\"><div class=\"MdBx spcXs vr\"><div class=\"MdTxt ExAlgC fxC0 ExWrap ExWB\"><p>RADISTI TEAM BOTS</p></div></div></div><div class=\"t1Hero\"><div class=\"MdImg ExFull ExFit\"><div><a style=\"padding-bottom:100%;\"><span style=\"background-image:url('https://obs.line-scdn.net/0h-2eC-Lnrch1YOljyjdkNSmR_fHAvFHRVIAttei07KS1zXzRDMAk8eio4KyhxWDNMM1RoK3g8filz');\"></span></a></div></div></div><div class=\"ExHasFooter t1Body\"><div class=\"spcMd MdBx vr\"><div class=\"spcMd MdBx hr\"><div class=\"MdImg ExSm ExFit\"><div><a style=\"padding-bottom:100%;\"><span style=\"background-image:url('https://i.ibb.co/vd9PLVy/1549594117625.jpg');\"></span></a></div></div><div class=\"fl0 MdSep\"></div><div class=\"MdTxt ExWrap\"><p>NAMA:</p><p>\ud83e\udd82\u2767\u2765\u256c\u2550\u0f74\u0f72\u0f74\u0f72 iwedPSO\u2694\u2767\u2765</p></div></div><div class=\"fl0 MdSep\"></div><div class=\"spcMd MdBx hr\"><div class=\"MdImg ExSm ExFit\"><div><a style=\"padding-bottom:100%;\"><span style=\"background-image:url('https://info-menarik.net/wp-content/uploads/2014/11/Membuat-Animasi-Format-GIF-1.gif');\"></span></a></div></div><div class=\"fl0 MdSep\"></div><div class=\"MdTxt ExWrap ExXs\"><p>PROFILE:</p></div></div></div></div><div class=\"t1Footer\"><div class=\"MdBx vr\"><div class=\"spcMd mdBxSpacer fl0\"></div><div class=\"ExBtn1 MdBtn\"><a class=\"fxC1\" href=\"http://line.me/ti/p/~radistiutama\"><div>KLIK ME</div></a></div></div></div></div><script src=\"https://d.line-scdn.net/n/line_flexible_msg/js/app_1535978521.js\"></script><script>(function(global){var m;if(typeof global.FM===\"function\"){m=new global.FM}if(typeof global.htmlMsgScrollOut===\"undefined\"){global.htmlMsgScrollOut=function(){}}global.htmlMsgReady=function(env,state){global.isReady=true;if(global.isException||typeof m===\"undefined\"){global.ERR()}else{m.ready(env,state)}}})(window);</script></body></html>",
            "USE_FULL_WIDTH": "false",
            "USE_HORIZONTAL_SCROLL": "false",
            "USE_ROUND_CORNER": "false",
            "WIDTH_DIP": "300"
        },
        "contentType": 4,
        "createdTime": 1552482307202,
        "from": "ua38fa5037d9822fa1ae79ed7ed5104d5",
        "text": null
    },
    "9507681498194": {
        "contentMetadata": {
            "BOT_CHECK": "1",
            "BOT_MSGTYPE": "keyword_reply",
            "BOT_TO_MID": "c9ae491eb0ebe3cd9b4d83199364eba7d",
            "EMTVER": "3"
        },
        "contentType": 0,
        "createdTime": 1552482307127,
        "from": "u05b001551c897ad6a6e2ca6cecccd32e",
        "text": "Idihh...pamer kontak mulu..!!!!\udbc0\udc97\udbc0\udc97Lupa ingatan ya kak....\udbc0\udc79\udbc0\udc79"
    },
    "9507681498927": {
        "contentMetadata": {
            "ALT_TEXT": "RADISTI TEAM BOT",
            "BACKGROUND_COLOR": "00FFFFFF",
            "HTML_CONTENT": "<!doctype html><html><head><meta charset=\"UTF-8\"><meta name=\"viewport\" content=\"width=device-width, user-scalable=no, initial-scale=1, maximum-scale=1\"><meta name=\"format-detection\" content=\"telephone=no\"><script>var g=window;g.isReady=false;g.isException=false;g.ERR=function(){if(typeof g._htmlMsg===\"object\"){if(typeof g._htmlMsg.showErrorView===\"function\"){g._htmlMsg.showErrorView()}}};g.OERR=function(){g.isException=true;if(g.isReady){global.ERR()}};</script><link rel=\"stylesheet\" type=\"text/css\" href=\"https://d.line-scdn.net/n/line_flexible_msg/css/sp/main_1528964069.css\"><style type=\"text/css\">.fxC0 { color: #2500ff !important; } .fxC1 { background-color: #0d00ff !important; } </style></head><body style=\"margin: 0;\"><div class=\"T1 fxLTR\" dir=\"ltr\"><div class=\"t1Header\"><div class=\"MdBx spcXs vr\"><div class=\"MdTxt ExAlgC fxC0 ExWrap ExWB\"><p>RADISTI TEAM BOTS</p></div></div></div><div class=\"t1Hero\"><div class=\"MdImg ExFull ExFit\"><div><a style=\"padding-bottom:100%;\"><span style=\"background-image:url('https://obs.line-scdn.net/0h-2eC-Lnrch1YOljyjdkNSmR_fHAvFHRVIAttei07KS1zXzRDMAk8eio4KyhxWDNMM1RoK3g8filz');\"></span></a></div></div></div><div class=\"ExHasFooter t1Body\"><div class=\"spcMd MdBx vr\"><div class=\"spcMd MdBx hr\"><div class=\"MdImg ExSm ExFit\"><div><a style=\"padding-bottom:100%;\"><span style=\"background-image:url('https://i.ibb.co/vd9PLVy/1549594117625.jpg');\"></span></a></div></div><div class=\"fl0 MdSep\"></div><div class=\"MdTxt ExWrap\"><p>NAMA:</p><p>\ud83e\udd82\u2767\u2765\u256c\u2550\u0f74\u0f72\u0f74\u0f72 iwedPSO\u2694\u2767\u2765</p></div></div><div class=\"fl0 MdSep\"></div><div class=\"spcMd MdBx hr\"><div class=\"MdImg ExSm ExFit\"><div><a style=\"padding-bottom:100%;\"><span style=\"background-image:url('https://info-menarik.net/wp-content/uploads/2014/11/Membuat-Animasi-Format-GIF-1.gif');\"></span></a></div></div><div class=\"fl0 MdSep\"></div><div class=\"MdTxt ExWrap ExXs\"><p>PROFILE:</p></div></div></div></div><div class=\"t1Footer\"><div class=\"MdBx vr\"><div class=\"spcMd mdBxSpacer fl0\"></div><div class=\"ExBtn1 MdBtn\"><a class=\"fxC1\" href=\"http://line.me/ti/p/~radistiutama\"><div>KLIK ME</div></a></div></div></div></div><script src=\"https://d.line-scdn.net/n/line_flexible_msg/js/app_1535978521.js\"></script><script>(function(global){var m;if(typeof global.FM===\"function\"){m=new global.FM}if(typeof global.htmlMsgScrollOut===\"undefined\"){global.htmlMsgScrollOut=function(){}}global.htmlMsgReady=function(env,state){global.isReady=true;if(global.isException||typeof m===\"undefined\"){global.ERR()}else{m.ready(env,state)}}})(window);</script></body></html>",
            "USE_FULL_WIDTH": "false",
            "USE_HORIZONTAL_SCROLL": "false",
            "USE_ROUND_CORNER": "false",
            "WIDTH_DIP": "300"
        },
        "contentType": 4,
        "createdTime": 1552482307225,
        "from": "u6c5bf46280b97041bc8795e3d54ce536",
        "text": null
    },
    "9507681499967": {
        "contentMetadata": {
            "ALT_TEXT": "RADISTI TEAM BOT",
            "BACKGROUND_COLOR": "00FFFFFF",
            "HTML_CONTENT": "<!doctype html><html><head><meta charset=\"UTF-8\"><meta name=\"viewport\" content=\"width=device-width, user-scalable=no, initial-scale=1, maximum-scale=1\"><meta name=\"format-detection\" content=\"telephone=no\"><script>var g=window;g.isReady=false;g.isException=false;g.ERR=function(){if(typeof g._htmlMsg===\"object\"){if(typeof g._htmlMsg.showErrorView===\"function\"){g._htmlMsg.showErrorView()}}};g.OERR=function(){g.isException=true;if(g.isReady){global.ERR()}};</script><link rel=\"stylesheet\" type=\"text/css\" href=\"https://d.line-scdn.net/n/line_flexible_msg/css/sp/main_1528964069.css\"><style type=\"text/css\">.fxC0 { color: #2500ff !important; } .fxC1 { background-color: #0d00ff !important; } </style></head><body style=\"margin: 0;\"><div class=\"T1 fxLTR\" dir=\"ltr\"><div class=\"t1Header\"><div class=\"MdBx spcXs vr\"><div class=\"MdTxt ExAlgC fxC0 ExWrap ExWB\"><p>RADISTI TEAM BOTS</p></div></div></div><div class=\"t1Hero\"><div class=\"MdImg ExFull ExFit\"><div><a style=\"padding-bottom:100%;\"><span style=\"background-image:url('https://obs.line-scdn.net/0h-2eC-Lnrch1YOljyjdkNSmR_fHAvFHRVIAttei07KS1zXzRDMAk8eio4KyhxWDNMM1RoK3g8filz');\"></span></a></div></div></div><div class=\"ExHasFooter t1Body\"><div class=\"spcMd MdBx vr\"><div class=\"spcMd MdBx hr\"><div class=\"MdImg ExSm ExFit\"><div><a style=\"padding-bottom:100%;\"><span style=\"background-image:url('https://i.ibb.co/vd9PLVy/1549594117625.jpg');\"></span></a></div></div><div class=\"fl0 MdSep\"></div><div class=\"MdTxt ExWrap\"><p>NAMA:</p><p>\ud83e\udd82\u2767\u2765\u256c\u2550\u0f74\u0f72\u0f74\u0f72 iwedPSO\u2694\u2767\u2765</p></div></div><div class=\"fl0 MdSep\"></div><div class=\"spcMd MdBx hr\"><div class=\"MdImg ExSm ExFit\"><div><a style=\"padding-bottom:100%;\"><span style=\"background-image:url('https://info-menarik.net/wp-content/uploads/2014/11/Membuat-Animasi-Format-GIF-1.gif');\"></span></a></div></div><div class=\"fl0 MdSep\"></div><div class=\"MdTxt ExWrap ExXs\"><p>PROFILE:</p></div></div></div></div><div class=\"t1Footer\"><div class=\"MdBx vr\"><div class=\"spcMd mdBxSpacer fl0\"></div><div class=\"ExBtn1 MdBtn\"><a class=\"fxC1\" href=\"http://line.me/ti/p/~radistiutama\"><div>KLIK ME</div></a></div></div></div></div><script src=\"https://d.line-scdn.net/n/line_flexible_msg/js/app_1535978521.js\"></script><script>(function(global){var m;if(typeof global.FM===\"function\"){m=new global.FM}if(typeof global.htmlMsgScrollOut===\"undefined\"){global.htmlMsgScrollOut=function(){}}global.htmlMsgReady=function(env,state){global.isReady=true;if(global.isException||typeof m===\"undefined\"){global.ERR()}else{m.ready(env,state)}}})(window);</script></body></html>",
            "USE_FULL_WIDTH": "false",
            "USE_HORIZONTAL_SCROLL": "false",
            "USE_ROUND_CORNER": "false",
            "WIDTH_DIP": "300"
        },
        "contentType": 4,
        "createdTime": 1552482307233,
        "from": "u6ee0664139786a908017e22306deff5e",
        "text": null
    },
    "9507681502815": {
        "contentMetadata": {
            "ALT_TEXT": "RADISTI TEAM BOT",
            "BACKGROUND_COLOR": "00FFFFFF",
            "HTML_CONTENT": "<!doctype html><html><head><meta charset=\"UTF-8\"><meta name=\"viewport\" content=\"width=device-width, user-scalable=no, initial-scale=1, maximum-scale=1\"><meta name=\"format-detection\" content=\"telephone=no\"><script>var g=window;g.isReady=false;g.isException=false;g.ERR=function(){if(typeof g._htmlMsg===\"object\"){if(typeof g._htmlMsg.showErrorView===\"function\"){g._htmlMsg.showErrorView()}}};g.OERR=function(){g.isException=true;if(g.isReady){global.ERR()}};</script><link rel=\"stylesheet\" type=\"text/css\" href=\"https://d.line-scdn.net/n/line_flexible_msg/css/sp/main_1528964069.css\"><style type=\"text/css\">.fxC0 { color: #2500ff !important; } .fxC1 { background-color: #0d00ff !important; } </style></head><body style=\"margin: 0;\"><div class=\"T1 fxLTR\" dir=\"ltr\"><div class=\"t1Header\"><div class=\"MdBx spcXs vr\"><div class=\"MdTxt ExAlgC fxC0 ExWrap ExWB\"><p>RADISTI TEAM BOTS</p></div></div></div><div class=\"t1Hero\"><div class=\"MdImg ExFull ExFit\"><div><a style=\"padding-bottom:100%;\"><span style=\"background-image:url('https://obs.line-scdn.net/0h-2eC-Lnrch1YOljyjdkNSmR_fHAvFHRVIAttei07KS1zXzRDMAk8eio4KyhxWDNMM1RoK3g8filz');\"></span></a></div></div></div><div class=\"ExHasFooter t1Body\"><div class=\"spcMd MdBx vr\"><div class=\"spcMd MdBx hr\"><div class=\"MdImg ExSm ExFit\"><div><a style=\"padding-bottom:100%;\"><span style=\"background-image:url('https://i.ibb.co/vd9PLVy/1549594117625.jpg');\"></span></a></div></div><div class=\"fl0 MdSep\"></div><div class=\"MdTxt ExWrap\"><p>NAMA:</p><p>\ud83e\udd82\u2767\u2765\u256c\u2550\u0f74\u0f72\u0f74\u0f72 iwedPSO\u2694\u2767\u2765</p></div></div><div class=\"fl0 MdSep\"></div><div class=\"spcMd MdBx hr\"><div class=\"MdImg ExSm ExFit\"><div><a style=\"padding-bottom:100%;\"><span style=\"background-image:url('https://info-menarik.net/wp-content/uploads/2014/11/Membuat-Animasi-Format-GIF-1.gif');\"></span></a></div></div><div class=\"fl0 MdSep\"></div><div class=\"MdTxt ExWrap ExXs\"><p>PROFILE:</p></div></div></div></div><div class=\"t1Footer\"><div class=\"MdBx vr\"><div class=\"spcMd mdBxSpacer fl0\"></div><div class=\"ExBtn1 MdBtn\"><a class=\"fxC1\" href=\"http://line.me/ti/p/~radistiutama\"><div>KLIK ME</div></a></div></div></div></div><script src=\"https://d.line-scdn.net/n/line_flexible_msg/js/app_1535978521.js\"></script><script>(function(global){var m;if(typeof global.FM===\"function\"){m=new global.FM}if(typeof global.htmlMsgScrollOut===\"undefined\"){global.htmlMsgScrollOut=function(){}}global.htmlMsgReady=function(env,state){global.isReady=true;if(global.isException||typeof m===\"undefined\"){global.ERR()}else{m.ready(env,state)}}})(window);</script></body></html>",
            "USE_FULL_WIDTH": "false",
            "USE_HORIZONTAL_SCROLL": "false",
            "USE_ROUND_CORNER": "false",
            "WIDTH_DIP": "300"
        },
        "contentType": 4,
        "createdTime": 1552482307261,
        "from": "uc243c1751fbded37394e286abb3ab36c",
        "text": null
    },
    "9507681647668": {
        "contentMetadata": {
            "ALT_TEXT": "RADISTI TEAM BOT",
            "BACKGROUND_COLOR": "00FFFFFF",
            "HTML_CONTENT": "<!doctype html><html><head><meta charset=\"UTF-8\"><meta name=\"viewport\" content=\"width=device-width, user-scalable=no, initial-scale=1, maximum-scale=1\"><meta name=\"format-detection\" content=\"telephone=no\"><script>var g=window;g.isReady=false;g.isException=false;g.ERR=function(){if(typeof g._htmlMsg===\"object\"){if(typeof g._htmlMsg.showErrorView===\"function\"){g._htmlMsg.showErrorView()}}};g.OERR=function(){g.isException=true;if(g.isReady){global.ERR()}};</script><link rel=\"stylesheet\" type=\"text/css\" href=\"https://d.line-scdn.net/n/line_flexible_msg/css/sp/main_1528964069.css\"><style type=\"text/css\">.fxC0 { color: #000000 !important; } .fxC1 { background-color: #000000 !important; } </style></head><body style=\"margin: 0;\"><div class=\"T1 fxLTR\" dir=\"ltr\"><div class=\"t1Header\"><div class=\"MdBx spcXs vr\"><div class=\"MdTxt ExAlgC fxC0 ExWrap ExWB\"><p>RADISTI TEAM BOTS</p></div></div></div><div class=\"t1Hero\"><div class=\"MdImg ExFull ExFit\"><div><a style=\"padding-bottom:100%;\"><span style=\"background-image:url('https://obs.line-scdn.net/0h-2eC-Lnrch1YOljyjdkNSmR_fHAvFHRVIAttei07KS1zXzRDMAk8eio4KyhxWDNMM1RoK3g8filz');\"></span></a></div></div></div><div class=\"ExHasFooter t1Body\"><div class=\"spcMd MdBx vr\"><div class=\"spcMd MdBx hr\"><div class=\"MdImg ExSm ExFit\"><div><a style=\"padding-bottom:100%;\"><span style=\"background-image:url('https://i.ibb.co/vd9PLVy/1549594117625.jpg');\"></span></a></div></div><div class=\"fl0 MdSep\"></div><div class=\"MdTxt ExWrap\"><p>NAMA:</p><p>\ud83e\udd82\u2767\u2765\u256c\u2550\u0f74\u0f72\u0f74\u0f72 iwedPSO\u2694\u2767\u2765</p></div></div><div class=\"fl0 MdSep\"></div><div class=\"spcMd MdBx hr\"><div class=\"MdImg ExSm ExFit\"><div><a style=\"padding-bottom:100%;\"><span style=\"background-image:url('https://info-menarik.net/wp-content/uploads/2014/11/Membuat-Animasi-Format-GIF-1.gif');\"></span></a></div></div><div class=\"fl0 MdSep\"></div><div class=\"MdTxt ExWrap ExXs\"><p>PROFILE:</p></div></div></div></div><div class=\"t1Footer\"><div class=\"MdBx vr\"><div class=\"spcMd mdBxSpacer fl0\"></div><div class=\"ExBtn1 MdBtn\"><a class=\"fxC1\" href=\"http://line.me/ti/p/~radistiutama\"><div>KLIK ME</div></a></div></div></div></div><script src=\"https://d.line-scdn.net/n/line_flexible_msg/js/app_1535978521.js\"></script><script>(function(global){var m;if(typeof global.FM===\"function\"){m=new global.FM}if(typeof global.htmlMsgScrollOut===\"undefined\"){global.htmlMsgScrollOut=function(){}}global.htmlMsgReady=function(env,state){global.isReady=true;if(global.isException||typeof m===\"undefined\"){global.ERR()}else{m.ready(env,state)}}})(window);</script></body></html>",
            "USE_FULL_WIDTH": "false",
            "USE_HORIZONTAL_SCROLL": "false",
            "USE_ROUND_CORNER": "false",
            "WIDTH_DIP": "300"
        },
        "contentType": 4,
        "createdTime": 1552482308864,
        "from": "ud134cbd020e975960892558a13aa6dba",
        "text": null
    },
    "9507682026613": {
        "contentMetadata": {},
        "contentType": 0,
        "createdTime": 1552482312598,
        "from": "u931cfd7313b63713383b60149e0166cf",
        "text": "ws login"
    },
    "9507682653118": {
        "createdTime": 1552482319002,
        "from": "u09f59671aac95d08eea489002e6917da",
        "sticker": "http://dl.stickershop.line.naver.jp/stickershop/v1/sticker/135803794/android/sticker.png"
    },
    "9507683113043": {
        "createdTime": 1552482323659,
        "from": "uf5ade9343fd07061ff222f79586e5cb5",
        "sticker": "http://dl.stickershop.line.naver.jp/stickershop/v1/sticker/17863/android/sticker.png"
    },
    "9507683867021": {
        "contentMetadata": {},
        "contentType": 0,
        "createdTime": 1552482331442,
        "from": "u931cfd7313b63713383b60149e0166cf",
        "text": "om bejo"
    },
    "9507683909587": {
        "contentMetadata": {},
        "contentType": 0,
        "createdTime": 1552482331758,
        "from": "u09f59671aac95d08eea489002e6917da",
        "text": "Age beresaaaan"
    },
    "9507684466034": {
        "contentMetadata": {
            "MENTION": "{\"MENTIONEES\":[{\"S\":\"0\",\"E\":\"12\",\"M\":\"u16d91c94c7cb6c53de85869706f60f96\"}]}"
        },
        "contentType": 0,
        "createdTime": 1552482337425,
        "from": "ufa0a0417d09ed00f3645c76f9da47c57",
        "text": "@\u2570\u2500\u2550\u0939\u0908\ufdfdBejo\ufdfd ndi done"
    },
    "9507684655333": {
        "contentMetadata": {
            "MENTION": "{\"MENTIONEES\":[{\"S\":\"0\",\"E\":\"22\",\"M\":\"u09f59671aac95d08eea489002e6917da\"}]}"
        },
        "contentType": 0,
        "createdTime": 1552482339369,
        "from": "uf5ade9343fd07061ff222f79586e5cb5",
        "text": "@\ud83c\udf3f\ud83c\udf37Ale ramadhani\ud83c\udf37\ud83c\udf3f "
    },
    "9507684741260": {
        "createdTime": 1552482340280,
        "from": "ufa0a0417d09ed00f3645c76f9da47c57",
        "sticker": "http://dl.stickershop.line.naver.jp/stickershop/v1/sticker/15408187/android/sticker.png"
    },
    "9507684929141": {
        "createdTime": 1552482342142,
        "from": "ufa0a0417d09ed00f3645c76f9da47c57",
        "sticker": "http://dl.stickershop.line.naver.jp/stickershop/v1/sticker/15408187/android/sticker.png"
    },
    "9507685075843": {
        "contentMetadata": {},
        "contentType": 0,
        "createdTime": 1552482343629,
        "from": "u09f59671aac95d08eea489002e6917da",
        "text": "Ono juragan"
    },
    "9507685189693": {
        "contentMetadata": {},
        "contentType": 0,
        "createdTime": 1552482344868,
        "from": "uf5ade9343fd07061ff222f79586e5cb5",
        "text": "Nungil"
    },
    "9507685234187": {
        "contentMetadata": {},
        "contentType": 0,
        "createdTime": 1552482345288,
        "from": "u931cfd7313b63713383b60149e0166cf",
        "text": "pm om"
    },
    "9507685839438": {
        "contentMetadata": {},
        "contentType": 0,
        "createdTime": 1552482351500,
        "from": "u09f59671aac95d08eea489002e6917da",
        "text": "Biyuuhh"
    },
    "9507686633277": {
        "contentMetadata": {
            "MENTION": "{\"MENTIONEES\":[{\"S\":\"0\",\"E\":\"22\",\"M\":\"u09f59671aac95d08eea489002e6917da\"}]}"
        },
        "contentType": 0,
        "createdTime": 1552482359512,
        "from": "ufa0a0417d09ed00f3645c76f9da47c57",
        "text": "@\ud83c\udf3f\ud83c\udf37Ale ramadhani\ud83c\udf37\ud83c\udf3f pm bukak tpi ojo ngakak"
    },
    "9507686674294": {
        "contentMetadata": {},
        "contentType": 0,
        "createdTime": 1552482359894,
        "from": "u09f59671aac95d08eea489002e6917da",
        "text": "Kono podo pm kanda bejo"
    },
    "9507688604000": {
        "contentMetadata": {
            "MENTION": "{\"MENTIONEES\":[{\"S\":\"0\",\"E\":\"22\",\"M\":\"u09f59671aac95d08eea489002e6917da\"}]}"
        },
        "contentType": 0,
        "createdTime": 1552482379456,
        "from": "u931cfd7313b63713383b60149e0166cf",
        "text": "@\ud83c\udf3f\ud83c\udf37Ale ramadhani\ud83c\udf37\ud83c\udf3f \npm pean ra kok buka og buukk"
    },
    "9507689851263": {
        "contentMetadata": {},
        "contentType": 0,
        "createdTime": 1552482392055,
        "from": "u09f59671aac95d08eea489002e6917da",
        "text": "Aku ono juragan "
    },
    "9507690469953": {
        "contentMetadata": {},
        "contentType": 0,
        "createdTime": 1552482398321,
        "from": "u09f59671aac95d08eea489002e6917da",
        "text": "Age tas do minggatttt"
    },
    "9507690724554": {
        "contentMetadata": {},
        "contentType": 0,
        "createdTime": 1552482400866,
        "from": "u931cfd7313b63713383b60149e0166cf",
        "text": "Iyo buuukkk"
    },
    "9507690849770": {
        "contentMetadata": {},
        "contentType": 0,
        "createdTime": 1552482402117,
        "from": "u09f59671aac95d08eea489002e6917da",
        "text": "Rong adus gua"
    },
    "9507692074414": {
        "contentMetadata": {
            "MENTION": "{\"MENTIONEES\":[{\"S\":\"0\",\"E\":\"22\",\"M\":\"u09f59671aac95d08eea489002e6917da\"}]}"
        },
        "contentType": 0,
        "createdTime": 1552482414588,
        "from": "u931cfd7313b63713383b60149e0166cf",
        "text": "@\ud83c\udf3f\ud83c\udf37Ale ramadhani\ud83c\udf37\ud83c\udf3f \nRene tak dus i"
    },
    "9507697525649": {
        "createdTime": 1552482469716,
        "from": "u09f59671aac95d08eea489002e6917da",
        "sticker": "http://dl.stickershop.line.naver.jp/stickershop/v1/sticker/135803786/android/sticker.png"
    },
    "9507698781660": {
        "createdTime": 1552482482389,
        "from": "u931cfd7313b63713383b60149e0166cf",
        "sticker": "http://dl.stickershop.line.naver.jp/stickershop/v1/sticker/38489960/android/sticker.png"
    },
    "9507707414238": {
        "createdTime": 1552482570009,
        "from": "u09f59671aac95d08eea489002e6917da",
        "image": "client.png"
    },
    "9507707880333": {
        "createdTime": 1552482574627,
        "from": "u09f59671aac95d08eea489002e6917da",
        "sticker": "http://dl.stickershop.line.naver.jp/stickershop/v1/sticker/135803789/android/sticker.png"
    }
}